<class>
    <question>
        <questionText>There have been __ Nobel Prize laureates from Canada.</questionText>
        <answerOne>7</answerOne>
        <answerTwo>10</answerTwo>
        <answerThree>5</answerThree>
        <answerFour>22</answerFour>
        <correctAnswer>15</correctAnswer>
    </question>

    <question>
        <questionText>Babies have around ___ more bones than adults.</questionText>
        <answerOne>12</answerOne>
        <answerTwo>204</answerTwo>
        <answerThree>44</answerThree>
        <answerFour>63</answerFour>
        <correctAnswer>100</correctAnswer>
    </question>

    <question>
        <questionText>The Eiffel Tower can be __ taller during the summer.</questionText>
        <answerOne>0cm</answerOne>
        <answerTwo>109cm</answerTwo>
        <answerThree>50cm</answerThree>
        <answerFour>1cm</answerFour>
        <correctAnswer>15cm</correctAnswer>
    </question>

    <question>
        <questionText>20% of the Earth’s oxygen is produced by the___ forest.</questionText>
        <answerOne>The Primorye Forest</answerOne>
        <answerTwo>The Burmese tropical rain forest</answerTwo>
        <answerThree>Tropical forest of Congo</answerThree>
        <answerFour>The Taiga</answerFour>
        <correctAnswer>Amazon forest</correctAnswer>
    </question>

    <question>
        <questionText>____ is the only planet to spin clockwise.</questionText>
        <answerOne>Mars</answerOne>
        <answerTwo>Uranus</answerTwo>
        <answerThree>Mercury </answerThree>
        <answerFour>Jupiter</answerFour>
        <correctAnswer>Venus</correctAnswer>
    </question>

    <question>
        <questionText>Who invented the telephone?</questionText>
        <answerOne>John A Mc.Donald</answerOne>
        <answerTwo>Karl Marx</answerTwo>
        <answerThree>Isaac Newton</answerThree>
        <answerFour>Mahatma Ghandi </answerFour>
        <correctAnswer>Alexander Bell</correctAnswer>
    </question>

    <question>
        <questionText>Where was the earliest form of paper invented?</questionText>
        <answerOne>India</answerOne>
        <answerTwo>China</answerTwo>
        <answerThree>Mongolia</answerThree>
        <answerFour>Greece</answerFour>
        <correctAnswer>Egypt</correctAnswer>
    </question>

    <question>
        <questionText>Who built the first telescope?</questionText>
        <answerOne>Pablo Picasso</answerOne>
        <answerTwo>Leonardo da Vinci</answerTwo>
        <answerThree>Vladimir Putin</answerThree>
        <answerFour>Pythagoras</answerFour>
        <correctAnswer>Galileo Galilei</correctAnswer>
    </question>

    <question>
        <questionText>Who built the first gasoline-engine car?</questionText>
        <answerOne>Henry Ford</answerOne>
        <answerTwo>George B. Seldon</answerTwo>
        <answerThree>Rudolf Egg</answerThree>
        <answerFour>Edward Butler</answerFour>
        <correctAnswer>Karl Benz</correctAnswer>
    </question>

    <question>
        <questionText>What’s the name of the first satellite launched into space?</questionText>
        <answerOne>Piro</answerOne>
        <answerTwo>Pots</answerTwo>
        <answerThree>Dynasty</answerThree>
        <answerFour>Death Star</answerFour>
        <correctAnswer>Sputnik</correctAnswer>
    </question>

    <question>
        <questionText>Which year Was the first satellite launched into space? </questionText>
        <answerOne>1948</answerOne>
        <answerTwo>1992</answerTwo>
        <answerThree>1969</answerThree>
        <answerFour>1955</answerFour>
        <correctAnswer>1957</correctAnswer>
    </question>

    <question>
        <questionText>How many countries does the United States share a land border with?</questionText>
        <answerOne>1</answerOne>
        <answerTwo>4</answerTwo>
        <answerThree>3</answerThree>
        <answerFour>5</answerFour>
        <correctAnswer>2</correctAnswer>
    </question>

    <question>
        <questionText>What is the smallest country in the world?</questionText>
        <answerOne>Lichtenstein </answerOne>
        <answerTwo>Monaco</answerTwo>
        <answerThree>Marshall Islands</answerThree>
        <answerFour>Tuvalu</answerFour>
        <correctAnswer>Vatican City</correctAnswer>
    </question>

    <question>
        <questionText>What is the capital city of Spain?</questionText>
        <answerOne>Toledo</answerOne>
        <answerTwo>Seville</answerTwo>
        <answerThree>Barcelona</answerThree>
        <answerFour>Granada</answerFour>
        <correctAnswer>Madrid</correctAnswer>
    </question>

    <question>
        <questionText>What country is home to the tallest mountain of the world?</questionText>
        <answerOne>Canada</answerOne>
        <answerTwo>Switzerland </answerTwo>
        <answerThree>Pakistan</answerThree>
        <answerFour>India</answerFour>
        <correctAnswer>Nepal</correctAnswer>
    </question>

    <question>
        <questionText>Which country has the largest population in the world?</questionText>
        <answerOne>India</answerOne>
        <answerTwo>Africa</answerTwo>
        <answerThree>USA</answerThree>
        <answerFour>Russia</answerFour>
        <correctAnswer>China</correctAnswer>
    </question>

    <question>
        <questionText>What’s the largest US state?</questionText>
        <answerOne>Texas</answerOne>
        <answerTwo>California</answerTwo>
        <answerThree>Mississippi</answerThree>
        <answerFour>Florida</answerFour>
        <correctAnswer>Alaska</correctAnswer>
    </question>

    <question>
        <questionText>What is the only country that borders the United Kingdom?</questionText>
        <answerOne>Iceland</answerOne>
        <answerTwo>Germany </answerTwo>
        <answerThree>Spain </answerThree>
        <answerFour>Greenland</answerFour>
        <correctAnswer>Ireland</correctAnswer>
    </question>

    <question>
        <questionText>Where is the largest volcano on earth?</questionText>
        <answerOne>Philippines</answerOne>
        <answerTwo>Japan</answerTwo>
        <answerThree>USA</answerThree>
        <answerFour>India</answerFour>
        <correctAnswer>Hawaii </correctAnswer>
    </question>

    <question>
        <questionText>Which river flows through the Grand Canyon?</questionText>
        <answerOne>Truckee river</answerOne>
        <answerTwo>Virgin river</answerTwo>
        <answerThree>Death creek</answerThree>
        <answerFour>West Walker river</answerFour>
        <correctAnswer>Colorado river</correctAnswer>
    </question>

    <question>
        <questionText>When was The Great Depression?</questionText>
        <answerOne>1910s</answerOne>
        <answerTwo>1920s</answerTwo>
        <answerThree>1940s</answerThree>
        <answerFour>1900s</answerFour>
        <correctAnswer>1930s</correctAnswer>
    </question>

    <question>
        <questionText>When did the first human got to space?</questionText>
        <answerOne>1956</answerOne>
        <answerTwo>1977</answerTwo>
        <answerThree>1944</answerThree>
        <answerFour>1982</answerFour>
        <correctAnswer>1961</correctAnswer>
    </question>

    <question>
        <questionText>Who was the 42nd president of the United States?</questionText>
        <answerOne>Barack Obama</answerOne>
        <answerTwo>Joe Biden</answerTwo>
        <answerThree>Justin Trudeau</answerThree>
        <answerFour>Jean Chretien</answerFour>
        <correctAnswer>Bill Clinton</correctAnswer>
    </question>

    <question>
        <questionText>Which year did the Cold War start?</questionText>
        <answerOne>1956</answerOne>
        <answerTwo>1999</answerTwo>
        <answerThree>1920</answerThree>
        <answerFour>1940</answerFour>
        <correctAnswer>1950</correctAnswer>
    </question>

    <question>
        <questionText>Which year did World War II start?</questionText>
        <answerOne>1920</answerOne>
        <answerTwo>1856</answerTwo>
        <answerThree>1932</answerThree>
        <answerFour>1899</answerFour>
        <correctAnswer>1940</correctAnswer>
    </question>

    <question>
        <questionText>9/11 happened on which year?</questionText>
        <answerOne>1999</answerOne>
        <answerTwo>2005</answerTwo>
        <answerThree>2002</answerThree>
        <answerFour>2000</answerFour>
        <correctAnswer>2001</correctAnswer>
    </question>

    <question>
        <questionText>What is the name of the longest highway in the world?</questionText>
        <answerOne>Alberta Highway </answerOne>
        <answerTwo>Highway 550</answerTwo>
        <answerThree>King’s Highway</answerThree>
        <answerFour>Mackenzie Highway </answerFour>
        <correctAnswer>Trans-Canada Highway</correctAnswer>
    </question>

    <question>
        <questionText>How many time zones does Canada have?</questionText>
        <answerOne>3</answerOne>
        <answerTwo>12</answerTwo>
        <answerThree>8</answerThree>
        <answerFour>7</answerFour>
        <correctAnswer>6</correctAnswer>
    </question>

    <question>
        <questionText>Canada is home to what percentage of the world’s fresh water?</questionText>
        <answerOne>15%</answerOne>
        <answerTwo>33%</answerTwo>
        <answerThree>26%</answerThree>
        <answerFour>11%</answerFour>
        <correctAnswer>20%</correctAnswer>
    </question>

    <question>
        <questionText>Which Canadian province has the longest freshwater beach in the world?</questionText>
        <answerOne>British Columbia</answerOne>
        <answerTwo>Saskatchewan</answerTwo>
        <answerThree>Manitoba</answerThree>
        <answerFour>Alberta </answerFour>
        <correctAnswer>Ontario </correctAnswer>
    </question>

    <question>
        <questionText>Canada is ___ largest country in the world.</questionText>
        <answerOne>4th</answerOne>
        <answerTwo>1st</answerTwo>
        <answerThree>6th</answerThree>
        <answerFour>7th</answerFour>
        <correctAnswer>2nd</correctAnswer>
    </question>

    <question>
        <questionText>Canada has __ province and __ territories.</questionText>
        <answerOne>9,2</answerOne>
        <answerTwo>10,4</answerTwo>
        <answerThree>6,5</answerThree>
        <answerFour>7,5</answerFour>
        <correctAnswer>10,3</correctAnswer>
    </question>

    <question>
        <questionText>Which region has polar bear shaped license plates?</questionText>
        <answerOne>Wisconsin</answerOne>
        <answerTwo>Alberta</answerTwo>
        <answerThree>Alaska</answerThree>
        <answerFour>Yukon</answerFour>
        <correctAnswer>Nunavet</correctAnswer>
    </question>

    <question>
        <questionText>Daylight saving does not occur in this province.</questionText>
        <answerOne>Alaska </answerOne>
        <answerTwo>Africa</answerTwo>
        <answerThree>Manitoba</answerThree>
        <answerFour>Nova scotia</answerFour>
        <correctAnswer>Saskatchewan</correctAnswer>
    </question>

    <question>
        <questionText>Canada is the __ largest diamond producer in the world.</questionText>
        <answerOne>2nd</answerOne>
        <answerTwo>10th</answerTwo>
        <answerThree>1st</answerThree>
        <answerFour>21st</answerFour>
        <correctAnswer>5th</correctAnswer>
    </question>

    <question>
        <questionText>What was the lowest temperature ever recorded in the world?</questionText>
        <answerOne>-36.0C</answerOne>
        <answerTwo>-69.1C</answerTwo>
        <answerThree>-42.0C</answerThree>
        <answerFour>-100.0C</answerFour>
        <correctAnswer>-89.2C</correctAnswer>
    </question>

    <question>
        <questionText>What type of animal has an immortal species?</questionText>
        <answerOne>Sharks</answerOne>
        <answerTwo>Crocodiles</answerTwo>
        <answerThree>Whales</answerThree>
        <answerFour>Frogs</answerFour>
        <correctAnswer>Jellyfish</correctAnswer>
    </question>

    <question>
        <questionText>A snail can sleep for __ years at a time.</questionText>
        <answerOne>10</answerOne>
        <answerTwo>5</answerTwo>
        <answerThree>1</answerThree>
        <answerFour>16</answerFour>
        <correctAnswer>3</correctAnswer>
    </question>

    <question>
        <questionText>How many hearts does an octopus have></questionText>
        <answerOne>8</answerOne>
        <answerTwo>1</answerTwo>
        <answerThree>5</answerThree>
        <answerFour>2</answerFour>
        <correctAnswer>3</correctAnswer>
    </question>

    <question>
        <questionText>What skin colour does a polar bear have?</questionText>
        <answerOne>White</answerOne>
        <answerTwo>Brown</answerTwo>
        <answerThree>Gray</answerThree>
        <answerFour>Pink</answerFour>
        <correctAnswer>Black</correctAnswer>
    </question>

    <question>
        <questionText>Honeybees can flap their wings ___ times per second.</questionText>
        <answerOne>80</answerOne>
        <answerTwo>40</answerTwo>
        <answerThree>300</answerThree>
        <answerFour>150</answerFour>
        <correctAnswer>200</correctAnswer>
    </question>

    <question>
        <questionText>What position does a flamingo’s head have to be to eat?</questionText>
        <answerOne>forward</answerOne>
        <answerTwo>tilted </answerTwo>
        <answerThree>horizontal</answerThree>
        <answerFour>spinning </answerFour>
        <correctAnswer>upside down</correctAnswer>
    </question>

    <question>
        <questionText>Which type of mammal can fly?</questionText>
        <answerOne>Tree shrew</answerOne>
        <answerTwo>Flying squirrel </answerTwo>
        <answerThree>Colugo</answerThree>
        <answerFour>Flying mouse</answerFour>
        <correctAnswer>Bat</correctAnswer>
    </question>

    <question>
        <questionText>What is the female term of peacocks?</questionText>
        <answerOne>Hen</answerOne>
        <answerTwo>Peacock</answerTwo>
        <answerThree>Goose</answerThree>
        <answerFour>Cockerel</answerFour>
        <correctAnswer>Peahen</correctAnswer>
    </question>

    <question>
        <questionText>Which insect forms a heart with parts of their bodies during mating.</questionText>
        <answerOne>Butterfly </answerOne>
        <answerTwo>Mosquito </answerTwo>
        <answerThree>Spider</answerThree>
        <answerFour>Preying Mantis</answerFour>
        <correctAnswer>Dragon Fly</correctAnswer>
    </question>

    <question>
        <questionText>This animal’s fingerprints are so close to humans’ that they could taint crime scenes.</questionText>
        <answerOne>Gorilla</answerOne>
        <answerTwo>Wombat</answerTwo>
        <answerThree>Chimpanzee</answerThree>
        <answerFour>Orangutan </answerFour>
        <correctAnswer>Koala</correctAnswer>
    </question>

    <question>
        <questionText>which of the following is one of Canada’s national sports?</questionText>
        <answerOne>Curling</answerOne>
        <answerTwo>Dogsled </answerTwo>
        <answerThree>Cricket</answerThree>
        <answerFour>Tennis</answerFour>
        <correctAnswer>Hockey</correctAnswer>
    </question>

    <question>
        <questionText>The baseball glove was invented in which country.</questionText>
        <answerOne>Brazil</answerOne>
        <answerTwo>Germany</answerTwo>
        <answerThree>USA</answerThree>
        <answerFour>France</answerFour>
        <correctAnswer>Canada</correctAnswer>
    </question>

    <question>
        <questionText>1929</questionText>
        <answerOne>1955</answerOne>
        <answerTwo>1977</answerTwo>
        <answerThree>1999</answerThree>
        <answerFour>1944</answerFour>
        <correctAnswer>1967</correctAnswer>
    </question>

    <question>
        <questionText>The Olympics are held every ___ years.</questionText>
        <answerOne>1</answerOne>
        <answerTwo>2</answerTwo>
        <answerThree>5</answerThree>
        <answerFour>3</answerFour>
        <correctAnswer>4</correctAnswer>
    </question>

    <question>
        <questionText>What sport is dubbed the “King of sports?”</questionText>
        <answerOne>American Football</answerOne>
        <answerTwo>Basketball</answerTwo>
        <answerThree>Cricket</answerThree>
        <answerFour>Rugby</answerFour>
        <correctAnswer>Soccer/Football</correctAnswer>
    </question>

    <question>
        <questionText>How many players are on a baseball team?</questionText>
        <answerOne>12</answerOne>
        <answerTwo>6</answerTwo>
        <answerThree>10</answerThree>
        <answerFour>16</answerFour>
        <correctAnswer>9</correctAnswer>
    </question>

    <question>
        <questionText>Country with the most amount of summer Olympics competitions without winning any medals?</questionText>
        <answerOne>Argentina</answerOne>
        <answerTwo>Sri Lanka</answerTwo>
        <answerThree>Bosnia</answerThree>
        <answerFour>Turkey</answerFour>
        <correctAnswer>Liechtenstein</correctAnswer>
    </question>

    <question>
        <questionText>How many Olympics were held in countries that no longer exist?</questionText>
        <answerOne>5</answerOne>
        <answerTwo>0</answerTwo>
        <answerThree>1</answerThree>
        <answerFour>11</answerFour>
        <correctAnswer>3</correctAnswer>
    </question>

    <question>
        <questionText>What was the first featured-length animated movie ever released?</questionText>
        <answerOne>Lady and the Tramp</answerOne>
        <answerTwo>Cinderella</answerTwo>
        <answerThree>Pocahontas </answerThree>
        <answerFour>Lion King</answerFour>
        <correctAnswer>Snow White and the Seven Dwarfs</correctAnswer>
    </question>

    <question>
        <questionText>What is the name of the skyscraper in Die Hard?</questionText>
        <answerOne>Willis tower</answerOne>
        <answerTwo>Chrysler Building</answerTwo>
        <answerThree>Hard Plaza</answerThree>
        <answerFour>World Trade Center</answerFour>
        <correctAnswer>Nakatomi Plaza</correctAnswer>
    </question>

    <question>
        <questionText>For what movie did Steven Spielberg win his first Oscar for Best Director?</questionText>
        <answerOne>Indiana Jones</answerOne>
        <answerTwo>Catch Me if you can</answerTwo>
        <answerThree>The Terminal</answerThree>
        <answerFour>A.I Intelligence</answerFour>
        <correctAnswer>Schindler’s List</correctAnswer>
    </question>

    <question>
        <questionText>What’s Elvis Presley’s first hit in 1956?</questionText>
        <answerOne>Don’t Be Cruel</answerOne>
        <answerTwo>Burning Love</answerTwo>
        <answerThree>It’s Now or Never</answerThree>
        <answerFour>A Little Less Conversation</answerFour>
        <correctAnswer>Heartbreak Hotel </correctAnswer>
    </question>

    <question>
        <questionText>What pop singer is known as “The Material Girl?”</questionText>
        <answerOne>Tina Turner</answerOne>
        <answerTwo>Aretha Franklin</answerTwo>
        <answerThree>Diana Ross</answerThree>
        <answerFour>Billie Holiday</answerFour>
        <correctAnswer>Madonna</correctAnswer>
    </question>

    <question>
        <questionText>What movie did Duran Duran get their name from?</questionText>
        <answerOne>Save a Prayer</answerOne>
        <answerTwo>Hungry Like the Wolf</answerTwo>
        <answerThree>Ordinary World</answerThree>
        <answerFour>Come Undone</answerFour>
        <correctAnswer>Barbella</correctAnswer>
    </question>

    <question>
        <questionText>Elton John is known for what signature accessory?</questionText>
        <answerOne>Tweed coat</answerOne>
        <answerTwo>Hair</answerTwo>
        <answerThree>Trousers</answerThree>
        <answerFour>Yellow Blazer </answerFour>
        <correctAnswer>Eyeglasses</correctAnswer>
    </question>

    <question>
        <questionText>Who directed the movie "Groundhog Day"?</questionText>
        <answerOne>Alfred Hitchcock</answerOne>
        <answerTwo>Orson Welles</answerTwo>
        <answerThree>Quentin Tarantino</answerThree>
        <answerFour>Ridley Scott</answerFour>
        <correctAnswer>Harold Ramis</correctAnswer>
    </question>

    <question>
        <questionText>In the movie “Grease,” what was Rizzo’s first name?</questionText>
        <answerOne>Danny</answerOne>
        <answerTwo>Frenchy </answerTwo>
        <answerThree>Cha-Cha</answerThree>
        <answerFour>Marty</answerFour>
        <correctAnswer>Betty</correctAnswer>
    </question>

    <question>
        <questionText>Who was the drummer for the Beatles?</questionText>
        <answerOne>John Bonham</answerOne>
        <answerTwo>Neil Peart</answerTwo>
        <answerThree>Keith Moon</answerThree>
        <answerFour>Buddy Rich</answerFour>
        <correctAnswer>Ringo Starr</correctAnswer>
    </question>

    <question>
        <questionText>How many members were there in the Spice Girls?</questionText>
        <answerOne>2</answerOne>
        <answerTwo>4</answerTwo>
        <answerThree>8</answerThree>
        <answerFour>6</answerFour>
        <correctAnswer>5</correctAnswer>
    </question>

    <question>
        <questionText>What was Freddie Mercury’s real name?</questionText>
        <answerOne>Frenchy Boon</answerOne>
        <answerTwo>Ford Manas</answerTwo>
        <answerThree>Franco Bonham</answerThree>
        <answerFour>Frank Busla</answerFour>
        <correctAnswer>Frederick Bulsara</correctAnswer>
    </question>

    <question>
        <questionText>How many movies are there in the film series, The God Father?</questionText>
        <answerOne>2</answerOne>
        <answerTwo>18</answerTwo>
        <answerThree>6</answerThree>
        <answerFour>4</answerFour>
        <correctAnswer>3</correctAnswer>
    </question>

    <question>
        <questionText>What is Jack Nicholson’s famous line from The Shinning?</questionText>
        <answerOne>“All work and no play makes Jack a dull boy”</answerOne>
        <answerTwo>“What about Room 237?”</answerTwo>
        <answerThree>“All work and no play”</answerThree>
        <answerFour>“Luke, I am your father”</answerFour>
        <correctAnswer>"Here’s Johnny"</correctAnswer>
    </question>

    <question>
        <questionText>What day is Star Wars Day?</questionText>
        <answerOne>April 1</answerOne>
        <answerTwo>June 11</answerTwo>
        <answerThree>July 4</answerThree>
        <answerFour>May 1</answerFour>
        <correctAnswer>May 4</correctAnswer>
    </question>

    <question>
        <questionText>Where did Spam originate from?</questionText>
        <answerOne>Hawaii, US</answerOne>
        <answerTwo>Phillipines</answerTwo>
        <answerThree>Germany</answerThree>
        <answerFour>Japan</answerFour>
        <correctAnswer>Minnesota, US</correctAnswer>
    </question>

    <question>
        <questionText>What was the first food eaten in space?</questionText>
        <answerOne>Pudding</answerOne>
        <answerTwo>Donut</answerTwo>
        <answerThree>Trail-mix</answerThree>
        <answerFour>Jello</answerFour>
        <correctAnswer>Apple sauce </correctAnswer>
    </question>

    <question>
        <questionText>Mangoes inspired what pattern in clothes?</questionText>
        <answerOne>Herringbone</answerOne>
        <answerTwo>Plaid</answerTwo>
        <answerThree>Stripes</answerThree>
        <answerFour>Houdstooth</answerFour>
        <correctAnswer>Paisley</correctAnswer>
    </question>

    <question>
        <questionText>What fast food restaurant introduced its first modern-day drive through?</questionText>
        <answerOne>Jack in the Box</answerOne>
        <answerTwo>Burger King</answerTwo>
        <answerThree>Tim Hortons</answerThree>
        <answerFour>KFC</answerFour>
        <correctAnswer>Wendy's</correctAnswer>
    </question>

    <question>
        <questionText>What did McDonald’s restaurant first introduce in 1968?</questionText>
        <answerOne>McNuggets</answerOne>
        <answerTwo>Fillet-O-Fish</answerTwo>
        <answerThree>The Cheese burger</answerThree>
        <answerFour>Pancakes</answerFour>
        <correctAnswer>The Big Mac</correctAnswer>
    </question>

    <question>
        <questionText>What is the most used flavor enhancer in fast foods?</questionText>
        <answerOne>Salt </answerOne>
        <answerTwo>Pepper</answerTwo>
        <answerThree>Paprika</answerThree>
        <answerFour>Kosher Salt</answerFour>
        <correctAnswer>MSG</correctAnswer>
    </question>

    <question>
        <questionText>Canada became a country on ____.</questionText>
        <answerOne>July 1, 1850</answerOne>
        <answerTwo>June 1, 1867</answerTwo>
        <answerThree>July 30, 1855</answerThree>
        <answerFour>July 4, 1880</answerFour>
        <correctAnswer>July 1, 1867</correctAnswer>
    </question>

    <question>
        <questionText>Canada has how many official languages?</questionText>
        <answerOne>0</answerOne>
        <answerTwo>1</answerTwo>
        <answerThree>3</answerThree>
        <answerFour>6</answerFour>
        <correctAnswer>2</correctAnswer>
    </question>

    <question>
        <questionText>Canada got its flag in ____.</questionText>
        <answerOne>1887</answerOne>
        <answerTwo>1920</answerTwo>
        <answerThree>1977</answerThree>
        <answerFour>1855</answerFour>
        <correctAnswer>1965</correctAnswer>
    </question>

    <question>
        <questionText>The east coast of Canada was settled by ___ in approximately 1000 AD.</questionText>
        <answerOne>Spaniards</answerOne>
        <answerTwo>English</answerTwo>
        <answerThree>Germans</answerThree>
        <answerFour>Russians</answerFour>
        <correctAnswer>Vikings</correctAnswer>
    </question>

    <question>
        <questionText>What is the title of the Canadian Leader?</questionText>
        <answerOne>Supreme Chancellor</answerOne>
        <answerTwo>President</answerTwo>
        <answerThree>Lord</answerThree>
        <answerFour>King/Queen</answerFour>
        <correctAnswer>Prime minster </correctAnswer>
    </question>
</class>

